engine/__init__.py
engine/cli.py
engine/config.py
engine/embeddings.py
engine/patterns.py
engine/rollback.py
engine/client/__init__.py
engine/client/api.py
engine/client/auth.py
engine/context/__init__.py
engine/context/assembler.py
engine/indexer/__init__.py
engine/indexer/incremental.py
engine/indexer/python.py
engine/indexer/typescript.py
enginecli_dev-2.1.5.dist-info/METADATA
enginecli_dev-2.1.5.dist-info/WHEEL
enginecli_dev-2.1.5.dist-info/entry_points.txt
enginecli_dev-2.1.5.dist-info/top_level.txt
enginecli_dev-2.1.5.dist-info/RECORD
