Metadata-Version: 2.4
Name: enginecli-dev
Version: 2.1.5
Summary: AI-powered code generation CLI with context-aware intelligence
Author-email: Engine <hello@enginecli.dev>
License: Proprietary
Project-URL: Homepage, https://enginecli.dev
Project-URL: Documentation, https://docs.enginecli.dev
Project-URL: Repository, https://github.com/enginecli/engine-cli
Keywords: ai,code-generation,cli,developer-tools
Classifier: Development Status :: 4 - Beta
Classifier: Environment :: Console
Classifier: Intended Audience :: Developers
Classifier: Programming Language :: Python :: 3
Classifier: Programming Language :: Python :: 3.9
Classifier: Programming Language :: Python :: 3.10
Classifier: Programming Language :: Python :: 3.11
Classifier: Programming Language :: Python :: 3.12
Classifier: Topic :: Software Development :: Code Generators
Requires-Python: >=3.9
Requires-Dist: click>=8.0.0
Requires-Dist: rich>=13.0.0
Requires-Dist: httpx>=0.25.0
Provides-Extra: dev
Requires-Dist: pytest>=7.0.0; extra == "dev"
Requires-Dist: pytest-cov>=4.0.0; extra == "dev"
Requires-Dist: black>=23.0.0; extra == "dev"
Requires-Dist: ruff>=0.1.0; extra == "dev"
Provides-Extra: rag
Requires-Dist: sentence-transformers>=2.2.0; extra == "rag"
Requires-Dist: numpy>=1.24.0; extra == "rag"
